{"cameraMode":{"drawMode":0,"name":"Shaded","section":"Shading Mode"},"sceneLighting":false,"audioPlay":false,"sceneViewState":{"m_AlwaysRefresh":false,"showFog":true,"showSkybox":false,"showFlares":true,"showImageEffects":true,"showParticleSystems":true,"showVisualEffectGraphs":true,"m_FxEnabled":true},"in2DMode":false,"pivot":{"x":1.9234658479690552,"y":16.236249923706056,"z":-1.595577359199524},"rotation":{"x":-0.01446736790239811,"y":0.9843637347221375,"z":-0.14606356620788575,"w":-0.09747480601072312},"size":0.47106584906578066,"orthographic":false}